LISA_CNN_ExplainerV5/ExplainLISA.py
LISA_CNN_ExplainerV5/__init__.py
LISA_CNN_ExplainerV5-0.0.4.dist-info/LICENSE
LISA_CNN_ExplainerV5-0.0.4.dist-info/METADATA
LISA_CNN_ExplainerV5-0.0.4.dist-info/WHEEL
LISA_CNN_ExplainerV5-0.0.4.dist-info/top_level.txt
LISA_CNN_ExplainerV5-0.0.4.dist-info/RECORD
