Metadata-Version: 2.1
Name: LISA-CNN-ExplainerV5
Version: 0.0.4
Summary: Unified Explanation Provider For CNNs
Home-page: https://github.com/SudilHasitha/LISA_CNN_ExplainerV5
Author: Sudil H.P Abeyagunasekera
Author-email: <sudilhasithaa51@gmail.com>
License: UNKNOWN
Keywords: LIME,Integrated gradients,SHAP,Anchors,Explainable AI,XAI,CNN Explainer
Platform: UNKNOWN
Classifier: Development Status :: 1 - Planning
Classifier: Intended Audience :: Developers
Classifier: Programming Language :: Python :: 3
Classifier: Operating System :: Unix
Classifier: Operating System :: MacOS :: MacOS X
Classifier: Operating System :: Microsoft :: Windows
License-File: LICENSE
Requires-Dist: opencv-python
Requires-Dist: numpy
Requires-Dist: pandas
Requires-Dist: matplotlib
Requires-Dist: scipy
Requires-Dist: scikit-learn
Requires-Dist: lime
Requires-Dist: shap
Requires-Dist: alibi
Requires-Dist: scikit-image
